[{"playerId":8459289,"teams":["WSH"],"name":"Martin Brochu"},{"playerId":8458693,"teams":["SJS"],"name":"Sean Gauthier"},{"playerId":8462044,"teams":["CGY"],"name":"Jean-Sebastien Giguere"},{"playerId":8459541,"teams":["NYI","EDM"],"name":"Tommy Salo"},{"playerId":8458562,"teams":["STL"],"name":"Jamie McLennan"},{"playerId":8459549,"teams":["DET"],"name":"Norm Maracle"},{"playerId":8459140,"teams":["UTA"],"name":"Nikolai Khabibulin"},{"playerId":8462152,"teams":["NSH"],"name":"Chris Mason"},{"playerId":8462102,"teams":["PIT"],"name":"Jean-Sebastien Aubin"},{"playerId":8447775,"teams":["PHI"],"name":"Ron Hextall"},{"playerId":8458266,"teams":["DAL"],"name":"Roman Turek"},{"playerId":8456264,"teams":["NYI"],"name":"Wade Flaherty"},{"playerId":8460712,"teams":["NSH"],"name":"Tomas Vokoun"},{"playerId":8457866,"teams":["ANA"],"name":"Dominic Roussel"},{"playerId":8459081,"teams":["TBL"],"name":"Derek Wilkinson"},{"playerId":8456137,"teams":["NSH"],"name":"Mike Dunham"},{"playerId":8459432,"teams":["MTL","CHI"],"name":"Jocelyn Thibault"},{"playerId":8448535,"teams":["WSH"],"name":"Olie Kolzig"},{"playerId":8448382,"teams":["TOR"],"name":"Curtis Joseph"},{"playerId":8458615,"teams":["SJS"],"name":"Steve Shields"},{"playerId":8465093,"teams":["UTA"],"name":"Robert Esche"},{"playerId":8459306,"teams":["BOS"],"name":"Robbie Tallas"},{"playerId":8455710,"teams":["NJD"],"name":"Martin Brodeur"},{"playerId":8459451,"teams":["CGY"],"name":"Tyler Moss"},{"playerId":8459252,"teams":["CGY"],"name":"Fred Brathwaite"},{"playerId":8455994,"teams":["BOS"],"name":"Byron Dafoe"},{"playerId":8459463,"teams":["VAN"],"name":"Kevin Weekes"},{"playerId":8445275,"teams":["PIT"],"name":"Tom Barrasso"},{"playerId":8445470,"teams":["COL"],"name":"Craig Billington"},{"playerId":8462161,"teams":["STL"],"name":"Brent Johnson"},{"playerId":8459132,"teams":["EDM"],"name":"Steve Passmore"},{"playerId":8451837,"teams":["OTT"],"name":"Ron Tugnutt"},{"playerId":8462047,"teams":["BUF"],"name":"Martin Biron"},{"playerId":8452217,"teams":["SJS"],"name":"Mike Vernon"},{"playerId":8458576,"teams":["NYI"],"name":"Marcel Cousineau"},{"playerId":8446134,"teams":["MTL"],"name":"Frederic Chabot"},{"playerId":8446719,"teams":["EDM"],"name":"Bob Essensa"},{"playerId":8447715,"teams":["ANA"],"name":"Guy Hebert"},{"playerId":8459308,"teams":["LAK"],"name":"Manny Legace"},{"playerId":8465036,"teams":["CGY"],"name":"Tyrone Garner"},{"playerId":8452157,"teams":["PHI"],"name":"John Vanbiesbrouck"},{"playerId":8465962,"teams":["STL"],"name":"Rich Parent"},{"playerId":8452535,"teams":["CGY"],"name":"Ken Wregget"},{"playerId":8457969,"teams":["TBL"],"name":"Corey Schwab"},{"playerId":8447449,"teams":["CHI","MTL"],"name":"Jeff Hackett"},{"playerId":8446991,"teams":["STL"],"name":"Grant Fuhr"},{"playerId":8459365,"teams":["EDM","UTA"],"name":"Mikhail Shtalenkov"},{"playerId":8458988,"teams":["DAL"],"name":"Manny Fernandez"},{"playerId":8450651,"teams":["TBL","DET"],"name":"Bill Ranford"},{"playerId":8452246,"teams":["UTA"],"name":"Jimmy Waite"},{"playerId":8450833,"teams":["NYR"],"name":"Mike Richter"},{"playerId":8450743,"teams":["TOR"],"name":"Jeff Reese"},{"playerId":8458075,"teams":["VAN"],"name":"Garth Snow"},{"playerId":8447687,"teams":["BUF"],"name":"Dominik Hasek"},{"playerId":8451834,"teams":["WSH"],"name":"Rick Tabaracci"},{"playerId":8458680,"teams":["VAN"],"name":"Corey Hirsch"},{"playerId":8458800,"teams":["CHI","CGY"],"name":"Andrei Trefilov"},{"playerId":8462247,"teams":["TBL"],"name":"Zac Bierk"},{"playerId":8458968,"teams":["STL"],"name":"Jim Carey"},{"playerId":8450627,"teams":["TBL"],"name":"Daren Puppa"},{"playerId":8445386,"teams":["DAL"],"name":"Ed Belfour"},{"playerId":8445769,"teams":["FLA"],"name":"Sean Burke"},{"playerId":8459453,"teams":["UTA"],"name":"Scott Langkow"},{"playerId":8451013,"teams":["WSH"],"name":"Michael Rosati"},{"playerId":8460806,"teams":["BUF"],"name":"Dwayne Roloson"},{"playerId":8451860,"teams":["NJD"],"name":"Chris Terreri"},{"playerId":8456830,"teams":["CAR"],"name":"Trevor Kidd"},{"playerId":8460497,"teams":["LAK"],"name":"Jamie Storr"},{"playerId":8458568,"teams":["DET"],"name":"Chris Osgood"},{"playerId":8459198,"teams":["LAK"],"name":"Ryan Bach"},{"playerId":8460516,"teams":["NYR"],"name":"Dan Cloutier"},{"playerId":8460506,"teams":["NSH"],"name":"Eric Fichaud"},{"playerId":8462055,"teams":["COL"],"name":"Marc Denis"},{"playerId":8451033,"teams":["COL"],"name":"Patrick Roy"},{"playerId":8466165,"teams":["PHI"],"name":"Jean-Marc Pelletier"},{"playerId":8457714,"teams":["TOR","NYI"],"name":"Felix Potvin"},{"playerId":8464715,"teams":["PIT"],"name":"Peter Skudra"},{"playerId":8446829,"teams":["CHI"],"name":"Mark Fitzpatrick"},{"playerId":8446831,"teams":["LAK"],"name":"Stephane Fiset"},{"playerId":8459357,"teams":["DET","TBL"],"name":"Kevin Hodson"},{"playerId":8457791,"teams":["OTT"],"name":"Damian Rhodes"},{"playerId":8447709,"teams":["TOR"],"name":"Glenn Healy"},{"playerId":8456692,"teams":["CAR"],"name":"Arturs Irbe"},{"playerId":8460535,"teams":["MTL"],"name":"Jose Theodore"},{"playerId":8449474,"teams":["FLA"],"name":"Kirk McLean"}]