[{"name":"Travis Hamonic","teams":["DET"],"nat":"CAN","playerId":8474612},{"name":"Andrei Chibisov","teams":[],"nat":"RUS","playerId":8481642},{"name":"Nathan Gerbe","teams":[],"nat":"USA","playerId":8471804},{"name":"Matt Martin","teams":[],"nat":"CAN","playerId":8474709,"birthDate":"1971-04-30"},{"name":"Noel Acciari","teams":["PIT"],"nat":"USA","playerId":8478569},{"name":"Slater Koekkoek","teams":[],"nat":"CAN","playerId":8476886},{"name":"Yanni Gourde","teams":["TBL"],"nat":"CAN","playerId":8476826},{"name":"Zach Senyshyn","teams":[],"nat":"CAN","playerId":8478485},{"name":"Greg McKegg","teams":[],"nat":"CAN","playerId":8475735},{"name":"Brett Seney","teams":[],"nat":"CAN","playerId":8478881},{"name":"Milan Lucic","teams":[],"nat":"CAN","playerId":8473473},{"name":"Urho Vaakanainen","teams":["NYR"],"nat":"FIN","playerId":8480001},{"name":"Marko Dano","teams":[],"nat":"SVK","playerId":8477448},{"name":"Sean Couturier","teams":["PHI"],"nat":"CAN","playerId":8476461},{"name":"Nick Leddy","teams":["SJS"],"nat":"USA","playerId":8475181},{"name":"Alexander Radulov","teams":[],"nat":"RUS","playerId":8471228},{"name":"Kieffer Bellows","teams":[],"nat":"USA","playerId":8479356},{"name":"Paul Stastny","teams":[],"nat":"USA","playerId":8471669},{"name":"Kevin Rooney","teams":["UTA"],"nat":"USA","playerId":8479291},{"name":"Adrian Kempe","teams":["LAK"],"nat":"SWE","playerId":8477960},{"name":"Steven Kampfer","teams":[],"nat":"USA","playerId":8474000},{"name":"Radko Gudas","teams":["ANA"],"nat":"CZE","playerId":8475462},{"name":"Jonathan Toews","teams":["WPG"],"nat":"CAN","playerId":8473604},{"name":"Patrick Marleau","teams":[],"nat":"CAN","playerId":8466139},{"name":"Justin Bailey","teams":[],"nat":"USA","playerId":8477473},{"name":"Nikita Zadorov","teams":["BOS"],"nat":"RUS","playerId":8477507},{"name":"Mark Giordano","teams":[],"nat":"CAN","playerId":8470966},{"name":"Boo Nieves","teams":[],"nat":"USA","playerId":8476922},{"name":"Joel Armia","teams":["LAK"],"nat":"FIN","playerId":8476469},{"name":"Riley Stillman","teams":["EDM"],"nat":"CAN","playerId":8479388},{"name":"Duncan Keith","teams":[],"nat":"CAN","playerId":8470281},{"name":"Conor Timmins","teams":["BUF"],"nat":"CAN","playerId":8479982},{"name":"Tomas Hertl","teams":["VGK"],"nat":"CZE","playerId":8476881},{"name":"Blake Lizotte","teams":["PIT"],"nat":"USA","playerId":8481481},{"name":"Emil Bemstrom","teams":[],"nat":"SWE","playerId":8480205},{"name":"Filip Zadina","teams":[],"nat":"CZE","playerId":8480821},{"name":"Ilya Mikheyev","teams":["CHI"],"nat":"RUS","playerId":8481624},{"name":"Jordan Weal","teams":[],"nat":"CAN","playerId":8475738},{"name":"Teuvo Teravainen","teams":["CHI"],"nat":"FIN","playerId":8476882},{"name":"Patric Hornqvist","teams":[],"nat":"SWE","playerId":8471887},{"name":"Zac Rinaldo","teams":[],"nat":"CAN","playerId":8474736},{"name":"Cody Eakin","teams":[],"nat":"CAN","playerId":8475236},{"name":"John Quenneville","teams":[],"nat":"CAN","playerId":8477961},{"name":"Josh Mahura","teams":["SEA"],"nat":"CAN","playerId":8479372},{"name":"Kiefer Sherwood","teams":["SJS"],"nat":"USA","playerId":8480748},{"name":"Jake Virtanen","teams":[],"nat":"CAN","playerId":8477937},{"name":"Brandon Sutter","teams":[],"nat":"CAN","playerId":8474091},{"name":"Alex DeBrincat","teams":["DET"],"nat":"USA","playerId":8479337},{"name":"Artem Anisimov","teams":[],"nat":"RUS","playerId":8473573},{"name":"Joshua Brown","teams":["EDM"],"nat":"CAN","playerId":8477384},{"name":"Jesper Fast","teams":[],"nat":"SWE","playerId":8475855},{"name":"Scott Sabourin","teams":["TBL"],"nat":"CAN","playerId":8477149},{"name":"Scott Harrington","teams":[],"nat":"CAN","playerId":8476449},{"name":"Alexander Wennberg","teams":["SJS"],"nat":"SWE","playerId":8477505},{"name":"Brandon Hagel","teams":["TBL"],"nat":"CAN","playerId":8479542},{"name":"Eric Robinson","teams":["CAR"],"nat":"USA","playerId":8480762},{"name":"Tyler Pitlick","teams":["MIN"],"nat":"USA","playerId":8475752},{"name":"Haydn Fleury","teams":["WPG"],"nat":"CAN","playerId":8477938},{"name":"Teddy Blueger","teams":["VAN"],"nat":"LVA","playerId":8476927},{"name":"Dylan DeMelo","teams":["WPG"],"nat":"CAN","playerId":8476331},{"name":"Tobias Rieder","teams":[],"nat":"GER","playerId":8476356},{"name":"Jani Hakanpää","teams":[],"nat":"FIN","playerId":8475825},{"name":"Dante Fabbro","teams":["CBJ"],"nat":"CAN","playerId":8479371},{"name":"Joakim Nygard","teams":[],"nat":"SWE","playerId":8481638},{"name":"Brett Connolly","teams":[],"nat":"CAN","playerId":8475792},{"name":"Dalton Smith","teams":[],"nat":"CAN","playerId":8475748},{"name":"Joel Farabee","teams":["CGY"],"nat":"USA","playerId":8480797},{"name":"Carl Soderberg","teams":[],"nat":"SWE","playerId":8471262},{"name":"Brandon Tanev","teams":["UTA"],"nat":"CAN","playerId":8479293},{"name":"Zach Whitecloud","teams":["CGY"],"nat":"CAN","playerId":8480727},{"name":"Sam Carrick","teams":["BUF"],"nat":"CAN","playerId":8475842},{"name":"Joakim Nordstrom","teams":[],"nat":"SWE","playerId":8475807},{"name":"Timo Meier","teams":["NJD"],"nat":"SUI","playerId":8478414},{"name":"Xavier Ouellet","teams":[],"nat":"FRA","playerId":8476443},{"name":"Pavel Zacha","teams":["BOS"],"nat":"CZE","playerId":8478401},{"name":"Filip Forsberg","teams":["NSH"],"nat":"SWE","playerId":8476887},{"name":"Mitch Marner","teams":["VGK"],"nat":"CAN","playerId":8478483},{"name":"Jake Evans","teams":["MTL"],"nat":"CAN","playerId":8478133},{"name":"Roman Polak","teams":[],"nat":"CZE","playerId":8471392},{"name":"Brad Richardson","teams":[],"nat":"CAN","playerId":8470755},{"name":"Jeff Skinner","teams":[],"nat":"CAN","playerId":8475784},{"name":"Marc-Edouard Vlasic","teams":[],"nat":"CAN","playerId":8471709},{"name":"Maxime Lajoie","teams":[],"nat":"CAN","playerId":8479320},{"name":"Micheal Ferland","teams":[],"nat":"CAN","playerId":8475907},{"name":"Jaccob Slavin","teams":["CAR"],"nat":"USA","playerId":8476958},{"name":"Joel L'Esperance","teams":[],"nat":"USA","playerId":8480769},{"name":"Luke Kunin","teams":["FLA"],"nat":"USA","playerId":8479316},{"name":"Bryan Rust","teams":["PIT"],"nat":"USA","playerId":8475810},{"name":"Tyson Barrie","teams":[],"nat":"CAN","playerId":8475197},{"name":"Daniel Carr","teams":[],"nat":"CAN","playerId":8477901},{"name":"Oscar Klefbom","teams":[],"nat":"SWE","playerId":8476472},{"name":"Brady Tkachuk","teams":["OTT"],"nat":"USA","playerId":8480801},{"name":"Nick Ritchie","teams":[],"nat":"CAN","playerId":8477941},{"name":"Dan Hamhuis","teams":[],"nat":"CAN","playerId":8469465},{"name":"Justin Braun","teams":[],"nat":"USA","playerId":8474027},{"name":"Dryden Hunt","teams":["CGY"],"nat":"CAN","playerId":8478211},{"name":"Tyson Jost","teams":["NSH"],"nat":"CAN","playerId":8479370},{"name":"Nikita Zaitsev","teams":[],"nat":"RUS","playerId":8479458},{"name":"Connor Murphy","teams":["EDM"],"nat":"USA","playerId":8476473},{"name":"Justin Faulk","teams":["DET"],"nat":"USA","playerId":8475753},{"name":"Matt Calvert","teams":[],"nat":"CAN","playerId":8474685},{"name":"Adam Brooks","teams":[],"nat":"CAN","playerId":8478996},{"name":"Isac Lundeström","teams":["CBJ"],"nat":"SWE","playerId":8480806},{"name":"Kris Letang","teams":["PIT"],"nat":"CAN","playerId":8471724},{"name":"Troy Stecher","teams":["TOR"],"nat":"CAN","playerId":8479442},{"name":"Matt Tennyson","teams":[],"nat":"USA","playerId":8476807},{"name":"Patrick Maroon","teams":[],"nat":"USA","playerId":8474034},{"name":"Danny DeKeyser","teams":[],"nat":"USA","playerId":8477215},{"name":"German Rubtsov","teams":[],"nat":"RUS","playerId":8479424},{"name":"Cody Glass","teams":["NJD"],"nat":"CAN","playerId":8479996},{"name":"Jan Rutta","teams":[],"nat":"CZE","playerId":8480172},{"name":"Nick Bonino","teams":[],"nat":"USA","playerId":8474009},{"name":"Brendan Perlini","teams":[],"nat":"GBR","playerId":8477943},{"name":"Ben Hutton","teams":["VGK"],"nat":"CAN","playerId":8477018},{"name":"Dillon Dube","teams":[],"nat":"CAN","playerId":8479346},{"name":"Brian Dumoulin","teams":["LAK"],"nat":"USA","playerId":8475208},{"name":"Mikhail Sergachev","teams":["UTA"],"nat":"RUS","playerId":8479410},{"name":"Shea Theodore","teams":["VGK"],"nat":"CAN","playerId":8477447},{"name":"Brady Skjei","teams":["NSH"],"nat":"USA","playerId":8476869},{"name":"David Backes","teams":[],"nat":"USA","playerId":8470655},{"name":"Victor Mete","teams":[],"nat":"CAN","playerId":8479376},{"name":"Tyler Ennis","teams":[],"nat":"CAN","playerId":8474589},{"name":"Klim Kostin","teams":[],"nat":"RUS","playerId":8480011},{"name":"T.J. Oshie","teams":[],"nat":"USA","playerId":8471698},{"name":"Troy Brouwer","teams":[],"nat":"CAN","playerId":8471426},{"name":"Andy Andreoff","teams":[],"nat":"CAN","playerId":8476404},{"name":"Dmitry Orlov","teams":["SJS"],"nat":"RUS","playerId":8475200},{"name":"Jake Middleton","teams":["MIN"],"nat":"CAN","playerId":8478136},{"name":"MacKenzie Weegar","teams":["UTA"],"nat":"CAN","playerId":8477346},{"name":"Tyler Motte","teams":[],"nat":"USA","playerId":8477353},{"name":"Shayne Gostisbehere","teams":["CAR"],"nat":"USA","playerId":8476906},{"name":"Ivan Barbashev","teams":["VGK"],"nat":"RUS","playerId":8477964},{"name":"Nathan Beaulieu","teams":[],"nat":"CAN","playerId":8476470},{"name":"Joakim Ryan","teams":[],"nat":"USA","playerId":8477046},{"name":"Mark Barberio","teams":[],"nat":"CAN","playerId":8474717},{"name":"Mike Hoffman","teams":[],"nat":"CAN","playerId":8474884},{"name":"Jordan Greenway","teams":["BUF"],"nat":"USA","playerId":8478413},{"name":"Ben Chiarot","teams":["DET"],"nat":"CAN","playerId":8475279},{"name":"Colin White","teams":["SJS"],"nat":"USA","playerId":8478400,"birthDate":"1977-12-12"},{"name":"Andy Greene","teams":[],"nat":"USA","playerId":8472382},{"name":"Ryan Reaves","teams":["SJS"],"nat":"CAN","playerId":8471817},{"name":"Victor Hedman","teams":["TBL"],"nat":"SWE","playerId":8475167},{"name":"Chandler Stephenson","teams":["SEA"],"nat":"CAN","playerId":8476905},{"name":"Frederik Gauthier","teams":[],"nat":"CAN","playerId":8477512},{"name":"Colin Miller","teams":["WPG"],"nat":"CAN","playerId":8476525},{"name":"Morgan Frost","teams":["CGY"],"nat":"CAN","playerId":8480028},{"name":"Trevor Lewis","teams":[],"nat":"USA","playerId":8473453},{"name":"TJ Brodie","teams":[],"nat":"CAN","playerId":8474673},{"name":"Kyle Connor","teams":["WPG"],"nat":"USA","playerId":8478398},{"name":"Erik Karlsson","teams":["PIT"],"nat":"SWE","playerId":8474578},{"name":"Scott Mayfield","teams":["NYI"],"nat":"USA","playerId":8476429},{"name":"Olli Maatta","teams":["CGY"],"nat":"FIN","playerId":8476874},{"name":"Robert Hagg","teams":[],"nat":"SWE","playerId":8477462},{"name":"Melker Karlsson","teams":[],"nat":"SWE","playerId":8477922},{"name":"Eric Staal","teams":[],"nat":"CAN","playerId":8470595},{"name":"Brett Pesce","teams":["NJD"],"nat":"USA","playerId":8477488},{"name":"Brandon Manning","teams":[],"nat":"CAN","playerId":8475430},{"name":"Radek Faksa","teams":["DAL"],"nat":"CZE","playerId":8476889},{"name":"Vladislav Namestnikov","teams":["WPG"],"nat":"RUS","playerId":8476480},{"name":"Paul Byron","teams":[],"nat":"CAN","playerId":8474038},{"name":"P.K. Subban","teams":[],"nat":"CAN","playerId":8474056},{"name":"Joey Anderson","teams":["CHI"],"nat":"USA","playerId":8479315},{"name":"Vince Dunn","teams":["SEA"],"nat":"CAN","playerId":8478407},{"name":"Ryan Donato","teams":["CHI"],"nat":"USA","playerId":8477987},{"name":"Andrew Shaw","teams":[],"nat":"CAN","playerId":8476381},{"name":"Patrice Bergeron","teams":[],"nat":"CAN","playerId":8470638},{"name":"Nick Holden","teams":[],"nat":"CAN","playerId":8474207},{"name":"John Hayden","teams":["SEA"],"nat":"USA","playerId":8477401},{"name":"Taylor Hall","teams":["CAR"],"nat":"CAN","playerId":8475791,"birthDate":"1991-11-14"},{"name":"Austin Watson","teams":["DET"],"nat":"USA","playerId":8475766},{"name":"Craig Smith","teams":[],"nat":"USA","playerId":8475225},{"name":"Adam Pelech","teams":["NYI"],"nat":"CAN","playerId":8476917},{"name":"Noah Hanifin","teams":["VGK"],"nat":"USA","playerId":8478396},{"name":"Gustav Nyquist","teams":["WPG"],"nat":"SWE","playerId":8474679},{"name":"Noah Gregor","teams":["FLA"],"nat":"CAN","playerId":8479393},{"name":"Jordan Staal","teams":["CAR"],"nat":"CAN","playerId":8473533},{"name":"Nicklas Backstrom","teams":[],"nat":"SWE","playerId":8473563},{"name":"Ivan Provorov","teams":["CBJ"],"nat":"RUS","playerId":8478500},{"name":"Nicolas Roy","teams":["COL"],"nat":"CAN","playerId":8478462},{"name":"Jason Dickinson","teams":["EDM"],"nat":"CAN","playerId":8477450},{"name":"Nic Petan","teams":[],"nat":"CAN","playerId":8477464},{"name":"Josh Leivo","teams":[],"nat":"CAN","playerId":8476410},{"name":"Ryan Poehling","teams":["ANA"],"nat":"USA","playerId":8480068},{"name":"Gustav Lindström","teams":[],"nat":"SWE","playerId":8480184},{"name":"Jaden Schwartz","teams":["SEA"],"nat":"CAN","playerId":8475768},{"name":"Mason Appleton","teams":["DET"],"nat":"USA","playerId":8478891},{"name":"Greg Pateryn","teams":[],"nat":"USA","playerId":8474688},{"name":"Zdeno Chara","teams":[],"nat":"SVK","playerId":8465009},{"name":"Par Lindholm","teams":[],"nat":"SWE","playerId":8480944},{"name":"Jason Robertson","teams":["DAL"],"nat":"USA","playerId":8480027},{"name":"Nick Paul","teams":["TBL"],"nat":"CAN","playerId":8477426},{"name":"Gabriel Bourque","teams":[],"nat":"CAN","playerId":8475268},{"name":"Jeff Petry","teams":["MIN"],"nat":"USA","playerId":8473507},{"name":"Jayson Megna","teams":[],"nat":"USA","playerId":8477126},{"name":"Janne Kuokkanen","teams":[],"nat":"FIN","playerId":8479511},{"name":"Cale Fleury","teams":["SEA"],"nat":"CAN","playerId":8479985},{"name":"Brenden Dillon","teams":["NJD"],"nat":"CAN","playerId":8475455},{"name":"Nico Sturm","teams":["MIN"],"nat":"GER","playerId":8481477},{"name":"Darnell Nurse","teams":["EDM"],"nat":"CAN","playerId":8477498},{"name":"Sean Walker","teams":["CAR"],"nat":"CAN","playerId":8480336},{"name":"Hampus Lindholm","teams":["BOS"],"nat":"SWE","playerId":8476854},{"name":"Patrick Kane","teams":["DET"],"nat":"USA","playerId":8474141},{"name":"Michael Stone","teams":[],"nat":"CAN","playerId":8474628},{"name":"Elias Pettersson","teams":["VAN"],"nat":"SWE","playerId":8480012,"birthDate":"1998-11-12"},{"name":"Leo Komarov","teams":[],"nat":"FIN","playerId":8473463},{"name":"Sam Lafferty","teams":["CHI"],"nat":"USA","playerId":8478043},{"name":"Mikhail Vorobyev","teams":[],"nat":"RUS","playerId":8478844},{"name":"Travis Sanheim","teams":["PHI"],"nat":"CAN","playerId":8477948},{"name":"Matthew Benning","teams":["TOR"],"nat":"CAN","playerId":8476988},{"name":"Tyler Benson","teams":[],"nat":"CAN","playerId":8479347},{"name":"Derek Grant","teams":[],"nat":"CAN","playerId":8474683},{"name":"Roope Hintz","teams":["DAL"],"nat":"FIN","playerId":8478449},{"name":"Sam Bennett","teams":["FLA"],"nat":"CAN","playerId":8477935},{"name":"Ryan Carpenter","teams":[],"nat":"USA","playerId":8477846},{"name":"James Neal","teams":[],"nat":"CAN","playerId":8471707},{"name":"Mackenzie MacEachern","teams":["VAN"],"nat":"USA","playerId":8476907},{"name":"Ryan Hartman","teams":["MIN"],"nat":"USA","playerId":8477451},{"name":"Anton Stralman","teams":[],"nat":"SWE","playerId":8471873},{"name":"Luke Witkowski","teams":[],"nat":"USA","playerId":8474722},{"name":"Steven Fogarty","teams":[],"nat":"USA","playerId":8476396},{"name":"Austin Poganski","teams":[],"nat":"USA","playerId":8478040},{"name":"Johnny Boychuk","teams":[],"nat":"CAN","playerId":8470187},{"name":"Julien Gauthier","teams":["STL"],"nat":"CAN","playerId":8479328},{"name":"Jamie Benn","teams":["DAL"],"nat":"CAN","playerId":8473994},{"name":"Miles Wood","teams":["CBJ"],"nat":"USA","playerId":8477425},{"name":"Drake Batherson","teams":["OTT"],"nat":"CAN","playerId":8480208},{"name":"Barclay Goodrow","teams":["SJS"],"nat":"CAN","playerId":8476624},{"name":"Alec Martinez","teams":[],"nat":"USA","playerId":8474166},{"name":"Joe Thornton","teams":[],"nat":"CAN","playerId":8466138},{"name":"Thomas Di Pauli","teams":[],"nat":"USA","playerId":8476974},{"name":"Stephen Johns","teams":[],"nat":"USA","playerId":8475730},{"name":"Ryan Strome","teams":["CGY"],"nat":"CAN","playerId":8476458},{"name":"Alexander Kerfoot","teams":["UTA"],"nat":"CAN","playerId":8477021},{"name":"William Karlsson","teams":["VGK"],"nat":"SWE","playerId":8476448},{"name":"Damon Severson","teams":["CBJ"],"nat":"CAN","playerId":8476923},{"name":"Fredrik Claesson","teams":[],"nat":"SWE","playerId":8476368},{"name":"Paul Carey","teams":[],"nat":"USA","playerId":8474008},{"name":"Kevin Hayes","teams":["PIT"],"nat":"USA","playerId":8475763},{"name":"Josh Morrissey","teams":["WPG"],"nat":"CAN","playerId":8477504},{"name":"Anders Bjork","teams":[],"nat":"USA","playerId":8478075},{"name":"Ville Heinola","teams":["WPG"],"nat":"FIN","playerId":8481572},{"name":"Tyler Lewington","teams":[],"nat":"CAN","playerId":8477343},{"name":"Anthony Cirelli","teams":["TBL"],"nat":"CAN","playerId":8478519},{"name":"Jesper Bratt","teams":["NJD"],"nat":"SWE","playerId":8479407},{"name":"Rocco Grimaldi","teams":[],"nat":"USA","playerId":8476428},{"name":"Rasmus Ristolainen","teams":["PHI"],"nat":"FIN","playerId":8477499},{"name":"Christian Wolanin","teams":[],"nat":"CAN","playerId":8478846},{"name":"Gabriel Dumont","teams":[],"nat":"CAN","playerId":8475254},{"name":"Anders Lee","teams":["NYI"],"nat":"USA","playerId":8475314},{"name":"Esa Lindell","teams":["DAL"],"nat":"FIN","playerId":8476902},{"name":"Logan O'Connor","teams":["COL"],"nat":"USA","playerId":8481186},{"name":"Loui Eriksson","teams":[],"nat":"SWE","playerId":8470626},{"name":"Boone Jenner","teams":["CBJ"],"nat":"CAN","playerId":8476432},{"name":"Justin Holl","teams":["STL"],"nat":"USA","playerId":8475718},{"name":"Tom Wilson","teams":["WSH"],"nat":"CAN","playerId":8476880},{"name":"Kyle Okposo","teams":[],"nat":"USA","playerId":8473449},{"name":"Mark Borowiecki","teams":[],"nat":"CAN","playerId":8474697},{"name":"Joel Kellman","teams":[],"nat":"SWE","playerId":8481516},{"name":"Dale Weise","teams":[],"nat":"CAN","playerId":8474668},{"name":"Zach Hyman","teams":["EDM"],"nat":"CAN","playerId":8475786},{"name":"Brandon Saad","teams":["VGK"],"nat":"USA","playerId":8476438},{"name":"Korbinian Holzer","teams":[],"nat":"GER","playerId":8473560},{"name":"Brandon Davidson","teams":[],"nat":"CAN","playerId":8475869},{"name":"T.J. Tynan","teams":["COL"],"nat":"USA","playerId":8476391},{"name":"Nathan MacKinnon","teams":["COL"],"nat":"CAN","playerId":8477492},{"name":"Rudolfs Balcers","teams":[],"nat":"LVA","playerId":8478870},{"name":"Samuel Morin","teams":[],"nat":"CAN","playerId":8477502},{"name":"Nicolas Hague","teams":["NSH"],"nat":"CAN","playerId":8479980},{"name":"Casey Cizikas","teams":["NYI"],"nat":"CAN","playerId":8475231},{"name":"Ryan Pulock","teams":["NYI"],"nat":"CAN","playerId":8477506},{"name":"Torey Krug","teams":["STL"],"nat":"USA","playerId":8476792},{"name":"Justin Abdelkader","teams":[],"nat":"USA","playerId":8471716},{"name":"Devon Toews","teams":["COL"],"nat":"CAN","playerId":8478038},{"name":"Beck Malenstyn","teams":["BUF"],"nat":"CAN","playerId":8479359},{"name":"Taro Hirose","teams":[],"nat":"CAN","playerId":8481433},{"name":"Jesperi Kotkaniemi","teams":["CAR"],"nat":"FIN","playerId":8480829},{"name":"Lukas Vejdemo","teams":[],"nat":"SWE","playerId":8478838},{"name":"Rasmus Asplund","teams":[],"nat":"SWE","playerId":8479335},{"name":"Chase De Leo","teams":[],"nat":"USA","playerId":8478029},{"name":"Markus Granlund","teams":[],"nat":"FIN","playerId":8476440},{"name":"Kyle Turris","teams":[],"nat":"CAN","playerId":8474068},{"name":"Josh Manson","teams":["COL"],"nat":"CAN","playerId":8476312},{"name":"Zach Aston-Reese","teams":["CBJ"],"nat":"USA","playerId":8479944},{"name":"Evander Kane","teams":["VAN"],"nat":"CAN","playerId":8475169},{"name":"Nick Merkley","teams":[],"nat":"CAN","playerId":8478447},{"name":"Josh Jacobs","teams":[],"nat":"USA","playerId":8477972},{"name":"Sam Steel","teams":["DAL"],"nat":"CAN","playerId":8479351},{"name":"Nic Dowd","teams":["VGK"],"nat":"USA","playerId":8475343},{"name":"Brendan Gallagher","teams":["MTL"],"nat":"CAN","playerId":8475848},{"name":"Tomas Nosek","teams":["FLA"],"nat":"CZE","playerId":8477931},{"name":"Christoffer Ehn","teams":[],"nat":"SWE","playerId":8478036},{"name":"Derek Ryan","teams":[],"nat":"USA","playerId":8478585},{"name":"Alex Ovechkin","teams":["WSH"],"nat":"RUS","playerId":8471214},{"name":"Calle Rosen","teams":["STL"],"nat":"SWE","playerId":8480157},{"name":"Otto Koivula","teams":[],"nat":"FIN","playerId":8479526},{"name":"Carl Gunnarsson","teams":[],"nat":"SWE","playerId":8474125},{"name":"Erik Gustafsson","teams":["DET"],"nat":"SWE","playerId":8476979,"birthDate":"1988-12-15"},{"name":"Brennan Menell","teams":[],"nat":"USA","playerId":8479734},{"name":"Alexander Volkov","teams":[],"nat":"RUS","playerId":8480186},{"name":"Trevor van Riemsdyk","teams":["WSH"],"nat":"USA","playerId":8477845},{"name":"Evgeny Kuznetsov","teams":[],"nat":"RUS","playerId":8475744},{"name":"Jordan Szwarz","teams":[],"nat":"CAN","playerId":8475224},{"name":"Brian Boyle","teams":[],"nat":"USA","playerId":8470619},{"name":"Cole Bardreau","teams":[],"nat":"USA","playerId":8478367},{"name":"Tim Gettinger","teams":[],"nat":"USA","playerId":8479364},{"name":"Kirby Dach","teams":["MTL"],"nat":"CAN","playerId":8481523},{"name":"Eetu Luostarinen","teams":["FLA"],"nat":"FIN","playerId":8480185},{"name":"J.T. Compher","teams":["DET"],"nat":"USA","playerId":8477456},{"name":"John Tavares","teams":["TOR"],"nat":"CAN","playerId":8475166},{"name":"Derek Stepan","teams":[],"nat":"USA","playerId":8474613},{"name":"Kevin Labanc","teams":[],"nat":"USA","playerId":8478099},{"name":"Deryk Engelland","teams":[],"nat":"CAN","playerId":8468674},{"name":"Chris Tierney","teams":[],"nat":"CAN","playerId":8476919},{"name":"Anthony Angello","teams":[],"nat":"USA","playerId":8478074},{"name":"Mikkel Boedker","teams":[],"nat":"DNK","playerId":8474571},{"name":"Darren Helm","teams":[],"nat":"CAN","playerId":8471794},{"name":"Mikael Granlund","teams":["ANA"],"nat":"FIN","playerId":8475798},{"name":"Yakov Trenin","teams":["MIN"],"nat":"RUS","playerId":8478508},{"name":"Colton Sceviour","teams":[],"nat":"CAN","playerId":8474098},{"name":"Zack Kassian","teams":[],"nat":"CAN","playerId":8475178},{"name":"Michael Sgarbossa","teams":[],"nat":"CAN","playerId":8475958},{"name":"Victor Olofsson","teams":["CGY"],"nat":"SWE","playerId":8478109},{"name":"Dylan McIlrath","teams":["WSH"],"nat":"CAN","playerId":8475795},{"name":"Niklas Hjalmarsson","teams":[],"nat":"SWE","playerId":8471769},{"name":"Josh Norris","teams":["BUF"],"nat":"USA","playerId":8480064},{"name":"Connor McDavid","teams":["EDM"],"nat":"CAN","playerId":8478402},{"name":"Brandon Pirri","teams":[],"nat":"CAN","playerId":8475204},{"name":"Dominic Toninato","teams":["CHI"],"nat":"USA","playerId":8476952},{"name":"Dylan Sikura","teams":[],"nat":"CAN","playerId":8478106},{"name":"Joel Edmundson","teams":["LAK"],"nat":"CAN","playerId":8476441},{"name":"Artemi Panarin","teams":["LAK"],"nat":"RUS","playerId":8478550},{"name":"Jake Gardiner","teams":[],"nat":"USA","playerId":8474581},{"name":"Otto Leskinen","teams":[],"nat":"FIN","playerId":8481105},{"name":"Ethan Bear","teams":["NYI"],"nat":"CAN","playerId":8478451},{"name":"David Perron","teams":["DET"],"nat":"CAN","playerId":8474102},{"name":"Mika Zibanejad","teams":["NYR"],"nat":"SWE","playerId":8476459},{"name":"Gaetan Haas","teams":[],"nat":"SUI","playerId":8481813},{"name":"Will Butcher","teams":[],"nat":"USA","playerId":8477355},{"name":"Matthew Tkachuk","teams":["FLA"],"nat":"USA","playerId":8479314},{"name":"Bobby Ryan","teams":[],"nat":"USA","playerId":8471676},{"name":"Brent Seabrook","teams":[],"nat":"CAN","playerId":8470607},{"name":"Michael Chaput","teams":[],"nat":"CAN","playerId":8475808},{"name":"Martin Kaut","teams":["SJS"],"nat":"CZE","playerId":8480822},{"name":"Yannick Weber","teams":[],"nat":"SUI","playerId":8474134},{"name":"Chris Tanev","teams":["TOR"],"nat":"CAN","playerId":8475690},{"name":"Alexander Nylander","teams":[],"nat":"SWE","playerId":8479423},{"name":"Max Jones","teams":["EDM"],"nat":"USA","playerId":8479368},{"name":"Joel Kiviranta","teams":["COL"],"nat":"FIN","playerId":8481641},{"name":"Nikolai Knyzhov","teams":[],"nat":"RUS","playerId":8481812},{"name":"Ilya Lyubushkin","teams":["DAL"],"nat":"RUS","playerId":8480950},{"name":"Nate Thompson","teams":[],"nat":"USA","playerId":8470775},{"name":"Jack Johnson","teams":[],"nat":"USA","playerId":8471677},{"name":"Zachary Sanford","teams":[],"nat":"USA","playerId":8477482},{"name":"Radim Simek","teams":[],"nat":"CZE","playerId":8480160},{"name":"Logan Couture","teams":["SJS"],"nat":"CAN","playerId":8474053},{"name":"Aaron Ness","teams":[],"nat":"USA","playerId":8474604},{"name":"Charles Hudon","teams":[],"nat":"CAN","playerId":8476948},{"name":"Bo Horvat","teams":["NYI"],"nat":"CAN","playerId":8477500},{"name":"Chris Kreider","teams":["ANA"],"nat":"USA","playerId":8475184},{"name":"Jordie Benn","teams":[],"nat":"CAN","playerId":8474818},{"name":"Erik Johnson","teams":[],"nat":"USA","playerId":8473446},{"name":"Carsen Twarynski","teams":[],"nat":"CAN","playerId":8479358},{"name":"Ondrej Palat","teams":["NYI"],"nat":"CZE","playerId":8476292},{"name":"Brad Hunt","teams":[],"nat":"CAN","playerId":8476779},{"name":"Jordan Martinook","teams":["CAR"],"nat":"CAN","playerId":8476921},{"name":"Jansen Harkins","teams":["ANA"],"nat":"USA","playerId":8478424},{"name":"Dominik Kahun","teams":[],"nat":"GER","playerId":8480946},{"name":"Patrick Russell","teams":[],"nat":"DNK","playerId":8479466},{"name":"Noah Dobson","teams":["MTL"],"nat":"CAN","playerId":8480865},{"name":"Matt Nieto","teams":[],"nat":"USA","playerId":8476442},{"name":"Aleksander Barkov","teams":["FLA"],"nat":"FIN","playerId":8477493},{"name":"J.C. Beaudin","teams":[],"nat":"CAN","playerId":8478833},{"name":"Marco Scandella","teams":[],"nat":"CAN","playerId":8474618},{"name":"Robert Thomas","teams":["STL"],"nat":"CAN","playerId":8480023},{"name":"Jacob Trouba","teams":["ANA"],"nat":"USA","playerId":8476885},{"name":"Liam Foudy","teams":["NYI"],"nat":"CAN","playerId":8480853},{"name":"Morgan Rielly","teams":["TOR"],"nat":"CAN","playerId":8476853},{"name":"Casey Mittelstadt","teams":["BOS"],"nat":"USA","playerId":8479999},{"name":"Valeri Nichushkin","teams":["COL"],"nat":"RUS","playerId":8477501},{"name":"Rasmus Sandin","teams":["WSH"],"nat":"SWE","playerId":8480873},{"name":"Evan Rodrigues","teams":["FLA"],"nat":"CAN","playerId":8478542},{"name":"Brent Burns","teams":["COL"],"nat":"CAN","playerId":8470613},{"name":"Marcus Foligno","teams":["MIN"],"nat":"CAN","playerId":8475220},{"name":"Marcus Johansson","teams":["MIN"],"nat":"SWE","playerId":8475149},{"name":"Brendan Leipsic","teams":[],"nat":"CAN","playerId":8476894},{"name":"Mathieu Joseph","teams":["LAK"],"nat":"CAN","playerId":8478472},{"name":"Alexander Edler","teams":[],"nat":"SWE","playerId":8471303},{"name":"Cam Atkinson","teams":[],"nat":"USA","playerId":8474715},{"name":"Cody Ceci","teams":["LAK"],"nat":"CAN","playerId":8476879},{"name":"Brett Ritchie","teams":[],"nat":"CAN","playerId":8476439},{"name":"Mikael Backlund","teams":["CGY"],"nat":"SWE","playerId":8474150},{"name":"Logan Shaw","teams":[],"nat":"CAN","playerId":8476400},{"name":"Braydon Coburn","teams":[],"nat":"CAN","playerId":8470601},{"name":"Andreas Englund","teams":["NSH"],"nat":"SWE","playerId":8477971},{"name":"Brian Lashoff","teams":[],"nat":"USA","playerId":8474873},{"name":"Sami Niku","teams":[],"nat":"FIN","playerId":8478915},{"name":"Peter Cehlarik","teams":[],"nat":"SVK","playerId":8477417},{"name":"Ryan Murray","teams":[],"nat":"CAN","playerId":8476850},{"name":"Ryan O'Reilly","teams":["NSH"],"nat":"CAN","playerId":8475158},{"name":"Dalton Prout","teams":[],"nat":"CAN","playerId":8474774},{"name":"Sam Reinhart","teams":["FLA"],"nat":"CAN","playerId":8477933},{"name":"Jacob de la Rose","teams":[],"nat":"SWE","playerId":8477455},{"name":"Nikolai Prokhorkin","teams":[],"nat":"RUS","playerId":8476947},{"name":"Erik Cernak","teams":["TBL"],"nat":"SVK","playerId":8478416},{"name":"Christian Fischer","teams":[],"nat":"USA","playerId":8478432},{"name":"Nick Seeler","teams":["PHI"],"nat":"USA","playerId":8476372},{"name":"Pierre-Edouard Bellemare","teams":[],"nat":"FRA","playerId":8477930},{"name":"Marcus Sorensen","teams":[],"nat":"SWE","playerId":8475834},{"name":"Jujhar Khaira","teams":[],"nat":"CAN","playerId":8476915},{"name":"Micheal Haley","teams":[],"nat":"CAN","playerId":8474230},{"name":"Riley Sheahan","teams":[],"nat":"CAN","playerId":8475772},{"name":"Maxim Letunov","teams":[],"nat":"RUS","playerId":8477983},{"name":"Martin Necas","teams":["COL"],"nat":"CZE","playerId":8480039},{"name":"Anton Blidh","teams":["NYR"],"nat":"SWE","playerId":8477320},{"name":"Andrew Cogliano","teams":[],"nat":"CAN","playerId":8471699},{"name":"Nate Schmidt","teams":["UTA"],"nat":"USA","playerId":8477220},{"name":"Drake Caggiula","teams":[],"nat":"CAN","playerId":8479465},{"name":"Jake Walman","teams":["EDM"],"nat":"CAN","playerId":8478013},{"name":"Cameron Gaunce","teams":[],"nat":"CAN","playerId":8474611},{"name":"Dmitry Kulikov","teams":["FLA"],"nat":"RUS","playerId":8475179},{"name":"Alex Chiasson","teams":[],"nat":"CAN","playerId":8475163},{"name":"Jakub Voracek","teams":[],"nat":"CZE","playerId":8474161},{"name":"Evgeny Svechnikov","teams":[],"nat":"RUS","playerId":8478431},{"name":"Matt Niskanen","teams":[],"nat":"USA","playerId":8471702},{"name":"Kasperi Kapanen","teams":["EDM"],"nat":"FIN","playerId":8477953},{"name":"Dougie Hamilton","teams":["NJD"],"nat":"CAN","playerId":8476462},{"name":"Ben Street","teams":[],"nat":"CAN","playerId":8476043},{"name":"Brock McGinn","teams":[],"nat":"CAN","playerId":8476934},{"name":"Filip Chytil","teams":["VAN"],"nat":"CZE","playerId":8480078},{"name":"Brayden Point","teams":["TBL"],"nat":"CAN","playerId":8478010},{"name":"Ilya Kovalchuk","teams":[],"nat":"RUS","playerId":8469454},{"name":"Jared McCann","teams":["SEA"],"nat":"CAN","playerId":8477955},{"name":"Jake Guentzel","teams":["TBL"],"nat":"USA","playerId":8477404},{"name":"Anthony Beauvillier","teams":["WSH"],"nat":"CAN","playerId":8478463},{"name":"Derick Brassard","teams":[],"nat":"CAN","playerId":8473544},{"name":"Cedric Paquette","teams":[],"nat":"CAN","playerId":8476975},{"name":"Jakob Chychrun","teams":["WSH"],"nat":"CAN","playerId":8479345},{"name":"Blake Comeau","teams":[],"nat":"CAN","playerId":8471260},{"name":"Phillip Danault","teams":["MTL"],"nat":"CAN","playerId":8476479},{"name":"Jean-Sebastien Dea","teams":[],"nat":"CAN","playerId":8477520},{"name":"Phil Kessel","teams":[],"nat":"USA","playerId":8473548},{"name":"Calle Jarnkrok","teams":["TOR"],"nat":"SWE","playerId":8475714},{"name":"Nick Foligno","teams":["MIN"],"nat":"USA","playerId":8473422},{"name":"Jonathan Ericsson","teams":[],"nat":"SWE","playerId":8470318},{"name":"Carson Soucy","teams":["NYI"],"nat":"CAN","playerId":8477369},{"name":"Brayden McNabb","teams":["VGK"],"nat":"CAN","playerId":8475188},{"name":"Nino Niederreiter","teams":["WPG"],"nat":"SUI","playerId":8475799},{"name":"David Krejci","teams":[],"nat":"CZE","playerId":8471276},{"name":"Anton Lindholm","teams":[],"nat":"SWE","playerId":8478073},{"name":"Tucker Poolman","teams":[],"nat":"USA","playerId":8477359},{"name":"Ryan Dzingel","teams":[],"nat":"USA","playerId":8476288},{"name":"Connor Carrick","teams":[],"nat":"USA","playerId":8476941},{"name":"Pontus Aberg","teams":[],"nat":"SWE","playerId":8476857},{"name":"Nikolaj Ehlers","teams":["CAR"],"nat":"DNK","playerId":8477940},{"name":"David Savard","teams":[],"nat":"CAN","playerId":8475233},{"name":"Ryan McDonagh","teams":["TBL"],"nat":"USA","playerId":8474151},{"name":"Auston Matthews","teams":["TOR"],"nat":"USA","playerId":8479318},{"name":"Anthony Bitetto","teams":[],"nat":"USA","playerId":8475868},{"name":"Quinn Hughes","teams":["MIN"],"nat":"USA","playerId":8480800},{"name":"Buddy Robinson","teams":[],"nat":"USA","playerId":8477210},{"name":"Jon Merrill","teams":[],"nat":"USA","playerId":8475750},{"name":"Lucas Wallmark","teams":[],"nat":"SWE","playerId":8478027},{"name":"Clark Bishop","teams":["CGY"],"nat":"CAN","playerId":8478056},{"name":"CJ Suess","teams":[],"nat":"USA","playerId":8478058},{"name":"Kevin Fiala","teams":["LAK"],"nat":"SUI","playerId":8477942},{"name":"Keegan Kolesar","teams":["VGK"],"nat":"CAN","playerId":8478434},{"name":"Carl Grundstrom","teams":["PHI"],"nat":"SWE","playerId":8479336},{"name":"Christian Dvorak","teams":["PHI"],"nat":"USA","playerId":8477989},{"name":"Tyler Seguin","teams":["DAL"],"nat":"CAN","playerId":8475794},{"name":"Antti Suomela","teams":[],"nat":"FIN","playerId":8480965},{"name":"Mark Pysyk","teams":[],"nat":"CAN","playerId":8475796},{"name":"Gustav Olofsson","teams":["SEA"],"nat":"SWE","playerId":8477467},{"name":"Michael Frolik","teams":[],"nat":"CZE","playerId":8473564},{"name":"Alexander True","teams":[],"nat":"DNK","playerId":8480384},{"name":"Jordan Gross","teams":[],"nat":"USA","playerId":8480913},{"name":"Stefan Matteau","teams":[],"nat":"USA","playerId":8476870},{"name":"Mark Letestu","teams":[],"nat":"CAN","playerId":8473914},{"name":"Lucas Carlsson","teams":["SJS"],"nat":"SWE","playerId":8479523},{"name":"Alex Tuch","teams":["BUF"],"nat":"USA","playerId":8477949},{"name":"Chris Stewart","teams":[],"nat":"CAN","playerId":8473485},{"name":"Jonny Brodzinski","teams":["NYR"],"nat":"USA","playerId":8477380},{"name":"Andrew Copp","teams":["DET"],"nat":"USA","playerId":8477429},{"name":"Lars Eller","teams":["OTT"],"nat":"DNK","playerId":8474189},{"name":"Colin Blackwell","teams":["DAL"],"nat":"USA","playerId":8476278},{"name":"Luca Sbisa","teams":[],"nat":"SUI","playerId":8474579},{"name":"Paul LaDue","teams":[],"nat":"USA","playerId":8476983},{"name":"David Pastrnak","teams":["BOS"],"nat":"CZE","playerId":8477956},{"name":"Sean Kuraly","teams":["BOS"],"nat":"USA","playerId":8476374},{"name":"Matt Irwin","teams":[],"nat":"CAN","playerId":8475625},{"name":"Frans Nielsen","teams":[],"nat":"DNK","playerId":8470144},{"name":"Wayne Simmonds","teams":[],"nat":"CAN","playerId":8474190},{"name":"Jake McCabe","teams":["TOR"],"nat":"USA","playerId":8476931},{"name":"Jordan Eberle","teams":["SEA"],"nat":"CAN","playerId":8474586},{"name":"Brian Gibbons","teams":[],"nat":"USA","playerId":8476207},{"name":"Jamie Oleksiak","teams":["SEA"],"nat":"CAN","playerId":8476467},{"name":"Scott Laughton","teams":["LAK"],"nat":"CAN","playerId":8476872},{"name":"Elias Lindholm","teams":["BOS"],"nat":"SWE","playerId":8477496},{"name":"Maxime Comtois","teams":[],"nat":"CAN","playerId":8480031},{"name":"Jonathan Drouin","teams":["STL"],"nat":"CAN","playerId":8477494},{"name":"Pierre-Luc Dubois","teams":["WSH"],"nat":"CAN","playerId":8479400},{"name":"Drew Doughty","teams":["LAK"],"nat":"CAN","playerId":8474563},{"name":"Ondrej Kase","teams":[],"nat":"CZE","playerId":8478131},{"name":"Dominik Kubalik","teams":[],"nat":"CZE","playerId":8477330},{"name":"James van Riemsdyk","teams":["DET"],"nat":"USA","playerId":8474037},{"name":"Andrei Svechnikov","teams":["CAR"],"nat":"RUS","playerId":8480830},{"name":"Jean-Gabriel Pageau","teams":["NYI"],"nat":"CAN","playerId":8476419},{"name":"Philippe Myers","teams":["TOR"],"nat":"CAN","playerId":8479026},{"name":"Sam Gagner","teams":[],"nat":"CAN","playerId":8474040},{"name":"Kevin Stenlund","teams":["UTA"],"nat":"SWE","playerId":8478831},{"name":"Filip Chlapik","teams":[],"nat":"CZE","playerId":8478488},{"name":"Matt Duchene","teams":["DAL"],"nat":"CAN","playerId":8475168},{"name":"Vladislav Kamenev","teams":[],"nat":"RUS","playerId":8477973},{"name":"Riley Barber","teams":[],"nat":"USA","playerId":8477003},{"name":"Nico Hischier","teams":["NJD"],"nat":"SUI","playerId":8480002},{"name":"Cal Clutterbuck","teams":[],"nat":"CAN","playerId":8473504},{"name":"Mark Jankowski","teams":["CAR"],"nat":"CAN","playerId":8476873},{"name":"Andrew Mangiapane","teams":["CHI"],"nat":"CAN","playerId":8478233},{"name":"Morgan Geekie","teams":["BOS"],"nat":"CAN","playerId":8479987},{"name":"Vinnie Hinostroza","teams":["FLA"],"nat":"USA","playerId":8476994},{"name":"Richard Panik","teams":[],"nat":"SVK","playerId":8475209},{"name":"Matt Luff","teams":["NYI"],"nat":"CAN","playerId":8479644},{"name":"Sheldon Dries","teams":["DET"],"nat":"USA","playerId":8480326},{"name":"Jordan Oesterle","teams":["NSH"],"nat":"USA","playerId":8477851},{"name":"Jarred Tinordi","teams":[],"nat":"USA","playerId":8475797},{"name":"Jaret Anderson-Dolan","teams":["WPG"],"nat":"CAN","playerId":8479994},{"name":"Trevor Daley","teams":[],"nat":"CAN","playerId":8470110},{"name":"Lean Bergmann","teams":[],"nat":"GER","playerId":8481640},{"name":"Artturi Lehkonen","teams":["COL"],"nat":"FIN","playerId":8477476},{"name":"Jonas Brodin","teams":["MIN"],"nat":"SWE","playerId":8476463},{"name":"Vitaly Abramov","teams":[],"nat":"RUS","playerId":8479411},{"name":"Warren Foegele","teams":["OTT"],"nat":"CAN","playerId":8477998},{"name":"Travis Konecny","teams":["PHI"],"nat":"CAN","playerId":8478439},{"name":"Evgenii Dadonov","teams":["NJD"],"nat":"RUS","playerId":8474149},{"name":"Egor Korshkov","teams":[],"nat":"RUS","playerId":8479510},{"name":"Givani Smith","teams":["CAR"],"nat":"CAN","playerId":8479379},{"name":"Nazem Kadri","teams":["COL"],"nat":"CAN","playerId":8475172},{"name":"Andre Burakovsky","teams":["CHI"],"nat":"SWE","playerId":8477444},{"name":"Tyler Johnson","teams":[],"nat":"USA","playerId":8474870},{"name":"Aaron Ekblad","teams":["FLA"],"nat":"CAN","playerId":8477932},{"name":"John Gilmour","teams":[],"nat":"CAN","playerId":8477337},{"name":"Troy Terry","teams":["ANA"],"nat":"USA","playerId":8478873},{"name":"Alexander Yelesin","teams":[],"nat":"RUS","playerId":8481630},{"name":"Colin Wilson","teams":[],"nat":"USA","playerId":8474569},{"name":"Jesper Boqvist","teams":["FLA"],"nat":"SWE","playerId":8480003},{"name":"Brock Boeser","teams":["VAN"],"nat":"USA","playerId":8478444},{"name":"Zach Parise","teams":[],"nat":"USA","playerId":8470610},{"name":"Mats Zuccarello","teams":["MIN"],"nat":"NOR","playerId":8475692},{"name":"Jason Spezza","teams":[],"nat":"CAN","playerId":8469455},{"name":"Dennis Gilbert","teams":["OTT"],"nat":"USA","playerId":8478502},{"name":"Garnet Hathaway","teams":["PHI"],"nat":"USA","playerId":8477903},{"name":"Derek Forbort","teams":["VAN"],"nat":"USA","playerId":8475762},{"name":"Jeremy Lauzon","teams":["VGK"],"nat":"CAN","playerId":8478468},{"name":"Lawson Crouse","teams":["UTA"],"nat":"CAN","playerId":8478474},{"name":"Cam Fowler","teams":["STL"],"nat":"USA","playerId":8475764},{"name":"Jacob Larsson","teams":[],"nat":"SWE","playerId":8478491},{"name":"Taylor Fedun","teams":[],"nat":"CAN","playerId":8476166},{"name":"Patrik Laine","teams":["MTL"],"nat":"FIN","playerId":8479339},{"name":"Nikolay Goldobin","teams":[],"nat":"RUS","playerId":8477958},{"name":"John Carlson","teams":["ANA"],"nat":"USA","playerId":8474590},{"name":"Nick Suzuki","teams":["MTL"],"nat":"CAN","playerId":8480018},{"name":"Derrick Pouliot","teams":["CHI"],"nat":"CAN","playerId":8476884},{"name":"Aleksi Saarela","teams":[],"nat":"FIN","playerId":8478839},{"name":"Andrew Peeke","teams":["BOS"],"nat":"USA","playerId":8479369},{"name":"Jimmy Vesey","teams":[],"nat":"USA","playerId":8476918},{"name":"Mikey Anderson","teams":["LAK"],"nat":"USA","playerId":8479998},{"name":"Kevin Gravel","teams":["NSH"],"nat":"USA","playerId":8475857},{"name":"Jared Spurgeon","teams":["MIN"],"nat":"CAN","playerId":8474716},{"name":"Brock Nelson","teams":["COL"],"nat":"USA","playerId":8475754},{"name":"Danil Yurtaykin","teams":[],"nat":"RUS","playerId":8481515},{"name":"Tyler Graovac","teams":[],"nat":"CAN","playerId":8476344},{"name":"Anton Wedin","teams":[],"nat":"SWE","playerId":8481637},{"name":"Michael Del Zotto","teams":[],"nat":"CAN","playerId":8474584},{"name":"Dustin Brown","teams":[],"nat":"USA","playerId":8470606},{"name":"Jack Hughes","teams":["NJD"],"nat":"USA","playerId":8481559},{"name":"Michael Amadio","teams":["OTT"],"nat":"CAN","playerId":8478020},{"name":"Caleb Jones","teams":["PIT"],"nat":"USA","playerId":8478452},{"name":"Jake DeBrusk","teams":["VAN"],"nat":"CAN","playerId":8478498},{"name":"Jake Bischoff","teams":[],"nat":"USA","playerId":8476987},{"name":"Tobias Bjornfot","teams":["FLA"],"nat":"SWE","playerId":8481600},{"name":"Kyle Palmieri","teams":["NYI"],"nat":"USA","playerId":8475151},{"name":"Tyler Bertuzzi","teams":["CHI"],"nat":"CAN","playerId":8477479},{"name":"Anthony Mantha","teams":["PIT"],"nat":"CAN","playerId":8477511},{"name":"Matthew Highmore","teams":["NYI"],"nat":"CAN","playerId":8478146},{"name":"Matthew Peca","teams":[],"nat":"CAN","playerId":8476285},{"name":"Mario Ferraro","teams":["SJS"],"nat":"CAN","playerId":8479983},{"name":"Carter Verhaeghe","teams":["FLA"],"nat":"CAN","playerId":8477409},{"name":"Marcus Pettersson","teams":["VAN"],"nat":"SWE","playerId":8477969},{"name":"Adam Fox","teams":["NYR"],"nat":"USA","playerId":8479323},{"name":"Mirco Mueller","teams":[],"nat":"SUI","playerId":8477509},{"name":"Pierre Engvall","teams":["NYI"],"nat":"SWE","playerId":8478115},{"name":"Sean Monahan","teams":["CBJ"],"nat":"CAN","playerId":8477497},{"name":"Samuel Blais","teams":["MTL"],"nat":"CAN","playerId":8478104},{"name":"Alex Pietrangelo","teams":["VGK"],"nat":"CAN","playerId":8474565},{"name":"Max Veronneau","teams":[],"nat":"CAN","playerId":8480314},{"name":"Oskar Sundqvist","teams":["STL"],"nat":"SWE","playerId":8476897},{"name":"Adam Gaudette","teams":["SJS"],"nat":"USA","playerId":8478874},{"name":"Robby Fabbri","teams":["MIN"],"nat":"CAN","playerId":8477952},{"name":"Vladimir Tarasenko","teams":["MIN"],"nat":"RUS","playerId":8475765},{"name":"Clayton Keller","teams":["UTA"],"nat":"USA","playerId":8479343},{"name":"Erik Brannstrom","teams":[],"nat":"SWE","playerId":8480073},{"name":"Frank Vatrano","teams":["ANA"],"nat":"USA","playerId":8478366},{"name":"Oliver Wahlstrom","teams":[],"nat":"USA","playerId":8480789},{"name":"Tanner Pearson","teams":["BUF"],"nat":"CAN","playerId":8476871},{"name":"Ryan MacInnis","teams":[],"nat":"USA","playerId":8477974},{"name":"Adam Henrique","teams":["EDM"],"nat":"CAN","playerId":8474641},{"name":"Riley Nash","teams":[],"nat":"CAN","playerId":8474062},{"name":"Adam Lowry","teams":["WPG"],"nat":"USA","playerId":8476392},{"name":"Ryan Johansen","teams":[],"nat":"CAN","playerId":8475793},{"name":"Jay Beagle","teams":[],"nat":"CAN","playerId":8474291},{"name":"Vladimir Sobotka","teams":[],"nat":"CZE","playerId":8471743},{"name":"Andreas Athanasiou","teams":[],"nat":"CAN","playerId":8476960},{"name":"Antoine Roussel","teams":[],"nat":"FRA","playerId":8474849},{"name":"Ashton Sautner","teams":[],"nat":"CAN","playerId":8477085},{"name":"Mathieu Perreault","teams":[],"nat":"CAN","playerId":8473618},{"name":"Joel Persson","teams":[],"nat":"SWE","playerId":8480940},{"name":"John Klingberg","teams":["SJS"],"nat":"SWE","playerId":8475906},{"name":"Zemgus Girgensons","teams":["TBL"],"nat":"LVA","playerId":8476878},{"name":"Carl Hagelin","teams":[],"nat":"SWE","playerId":8474176},{"name":"Johan Larsson","teams":[],"nat":"SWE","playerId":8475728},{"name":"Jack Studnicka","teams":["FLA"],"nat":"CAN","playerId":8480021},{"name":"Patrik Nemeth","teams":[],"nat":"SWE","playerId":8475747},{"name":"Viktor Arvidsson","teams":["BOS"],"nat":"SWE","playerId":8478042},{"name":"Trevor Moore","teams":["LAK"],"nat":"USA","playerId":8479675},{"name":"Kevin Connauton","teams":["UTA"],"nat":"CAN","playerId":8475246},{"name":"Connor Bunnaman","teams":[],"nat":"CAN","playerId":8479382},{"name":"Martin Frk","teams":[],"nat":"CZE","playerId":8476924},{"name":"Mathew Dumba","teams":["PIT"],"nat":"CAN","playerId":8476856},{"name":"Robert Bortuzzo","teams":[],"nat":"CAN","playerId":8474145},{"name":"Kyle Capobianco","teams":["DAL"],"nat":"CAN","playerId":8478476},{"name":"Tom Kuhnhackl","teams":[],"nat":"GER","playerId":8475832},{"name":"Valentin Zykov","teams":[],"nat":"RUS","playerId":8477458},{"name":"Kevin Shattenkirk","teams":[],"nat":"USA","playerId":8474031},{"name":"Henri Jokiharju","teams":["BOS"],"nat":"FIN","playerId":8480035},{"name":"Keith Yandle","teams":[],"nat":"USA","playerId":8471735},{"name":"Mathieu Olivier","teams":["CBJ"],"nat":"USA","playerId":8479671},{"name":"Max Pacioretty","teams":[],"nat":"USA","playerId":8474157},{"name":"Ryan Ellis","teams":["CHI"],"nat":"CAN","playerId":8475176},{"name":"Joel Eriksson Ek","teams":["MIN"],"nat":"SWE","playerId":8478493},{"name":"Kurtis MacDermid","teams":["OTT"],"nat":"CAN","playerId":8477073},{"name":"Michael Raffl","teams":[],"nat":"AUT","playerId":8477290},{"name":"Matt Grzelcyk","teams":["CHI"],"nat":"USA","playerId":8476891},{"name":"Mikko Rantanen","teams":["DAL"],"nat":"FIN","playerId":8478420},{"name":"Rasmus Andersson","teams":["VGK"],"nat":"SWE","playerId":8478397},{"name":"Gabriel Carlsson","teams":[],"nat":"SWE","playerId":8478506},{"name":"Ryan Suter","teams":[],"nat":"USA","playerId":8470600},{"name":"Sami Vatanen","teams":[],"nat":"FIN","playerId":8475222},{"name":"John Marino","teams":["UTA"],"nat":"USA","playerId":8478507},{"name":"Jason Zucker","teams":["BUF"],"nat":"USA","playerId":8475722},{"name":"John Moore","teams":[],"nat":"USA","playerId":8475186},{"name":"Matt Roy","teams":["WSH"],"nat":"USA","playerId":8478911},{"name":"Neal Pionk","teams":["WPG"],"nat":"USA","playerId":8480145},{"name":"Thomas Chabot","teams":["OTT"],"nat":"CAN","playerId":8478469},{"name":"Sebastian Aho","teams":["CAR"],"nat":"FIN","playerId":8478427,"birthDate":"1997-07-26"},{"name":"Patrick Brown","teams":["BOS"],"nat":"USA","playerId":8477887},{"name":"Tony DeAngelo","teams":["NYI"],"nat":"USA","playerId":8477950},{"name":"Joonas Donskoi","teams":[],"nat":"FIN","playerId":8475820},{"name":"Kaapo Kakko","teams":["SEA"],"nat":"FIN","playerId":8481554},{"name":"Alexandre Texier","teams":["MTL"],"nat":"FRA","playerId":8480074},{"name":"Jonathan Davidsson","teams":[],"nat":"SWE","playerId":8480247},{"name":"Gabriel Landeskog","teams":["COL"],"nat":"SWE","playerId":8476455},{"name":"Barrett Hayton","teams":["UTA"],"nat":"CAN","playerId":8480849},{"name":"Michael Dal Colle","teams":[],"nat":"CAN","playerId":8477936},{"name":"Tyler Myers","teams":["DAL"],"nat":"CAN","playerId":8474574},{"name":"Brett Howden","teams":["VGK"],"nat":"CAN","playerId":8479353},{"name":"Oliver Ekman-Larsson","teams":["TOR"],"nat":"SWE","playerId":8475171},{"name":"Alexander Steen","teams":[],"nat":"SWE","playerId":8470257},{"name":"Pavel Buchnevich","teams":["STL"],"nat":"RUS","playerId":8477402},{"name":"Justin Williams","teams":[],"nat":"CAN","playerId":8468508},{"name":"Brandon Montour","teams":["SEA"],"nat":"CAN","playerId":8477986},{"name":"Stefan Noesen","teams":["NJD"],"nat":"USA","playerId":8476474},{"name":"Josh Anderson","teams":["MTL"],"nat":"CAN","playerId":8476981},{"name":"Nathan Walker","teams":["STL"],"nat":"AUS","playerId":8477573},{"name":"Lias Andersson","teams":[],"nat":"SWE","playerId":8480072},{"name":"Danton Heinen","teams":["CBJ"],"nat":"CAN","playerId":8478046},{"name":"Mark Scheifele","teams":["WPG"],"nat":"CAN","playerId":8476460},{"name":"Nick Caamano","teams":[],"nat":"CAN","playerId":8479381},{"name":"Evgeni Malkin","teams":["PIT"],"nat":"RUS","playerId":8471215},{"name":"Nicolas Beaudin","teams":[],"nat":"CAN","playerId":8480814},{"name":"Gemel Smith","teams":[],"nat":"CAN","playerId":8476966},{"name":"Mark Friedman","teams":[],"nat":"CAN","playerId":8478017},{"name":"Timothy Liljegren","teams":["WSH"],"nat":"SWE","playerId":8480043},{"name":"Ryan Getzlaf","teams":[],"nat":"CAN","playerId":8470612},{"name":"Ryan Graves","teams":["PIT"],"nat":"CAN","playerId":8477435},{"name":"Connor Brown","teams":["NJD"],"nat":"CAN","playerId":8477015},{"name":"Colton Parayko","teams":["STL"],"nat":"CAN","playerId":8476892},{"name":"Colton White","teams":["NJD"],"nat":"CAN","playerId":8478841},{"name":"Luke Johnson","teams":[],"nat":"USA","playerId":8477366},{"name":"Josh Archibald","teams":[],"nat":"CAN","playerId":8476326},{"name":"Logan Brown","teams":["LAK"],"nat":"USA","playerId":8479366},{"name":"Jayce Hawryluk","teams":[],"nat":"CAN","playerId":8477963},{"name":"Mathew Barzal","teams":["NYI"],"nat":"CAN","playerId":8478445},{"name":"Rhett Gardner","teams":[],"nat":"CAN","playerId":8479587},{"name":"Luke Schenn","teams":["BUF"],"nat":"CAN","playerId":8474568},{"name":"Lawrence Pilut","teams":[],"nat":"SWE","playerId":8480935},{"name":"Nicolas Aube-Kubel","teams":["MIN"],"nat":"CAN","playerId":8477979},{"name":"Rasmus Dahlin","teams":["BUF"],"nat":"SWE","playerId":8480839},{"name":"Conor Garland","teams":["CBJ"],"nat":"USA","playerId":8478856},{"name":"Markus Nutivaara","teams":[],"nat":"FIN","playerId":8478906},{"name":"Valtteri Filppula","teams":[],"nat":"FIN","playerId":8470047},{"name":"Vincent Trocheck","teams":["NYR"],"nat":"USA","playerId":8476389},{"name":"Alex Galchenyuk","teams":[],"nat":"USA","playerId":8476851},{"name":"Scott Wilson","teams":[],"nat":"CAN","playerId":8476293},{"name":"Lukas Radil","teams":[],"nat":"CZE","playerId":8480780},{"name":"Colby Cave","teams":[],"nat":"CAN","playerId":8477529},{"name":"Erik Gudbranson","teams":["CBJ"],"nat":"CAN","playerId":8475790},{"name":"Austin Wagner","teams":[],"nat":"CAN","playerId":8478455},{"name":"Blake Coleman","teams":["CGY"],"nat":"USA","playerId":8476399},{"name":"Travis Boyd","teams":["TOR"],"nat":"USA","playerId":8476329},{"name":"Mattias Ekholm","teams":["EDM"],"nat":"SWE","playerId":8475218},{"name":"Denis Malgin","teams":[],"nat":"SUI","playerId":8478843},{"name":"William Lagesson","teams":["DET"],"nat":"SWE","playerId":8478021},{"name":"Justin Dowling","teams":["NYR"],"nat":"CAN","playerId":8475413},{"name":"Johnny Gaudreau","teams":[],"nat":"USA","playerId":8476346},{"name":"Connor Clifton","teams":["PIT"],"nat":"USA","playerId":8477365},{"name":"Nick Cousins","teams":["OTT"],"nat":"CAN","playerId":8476393},{"name":"Mike Reilly","teams":["CAR"],"nat":"USA","playerId":8476422},{"name":"David Kase","teams":[],"nat":"CZE","playerId":8478436},{"name":"Josh Bailey","teams":[],"nat":"CAN","playerId":8474573},{"name":"Joachim Blichfeld","teams":[],"nat":"DNK","playerId":8479571},{"name":"Zach Bogosian","teams":["MIN"],"nat":"USA","playerId":8474567},{"name":"Nicolas Deslauriers","teams":["CAR"],"nat":"CAN","playerId":8475235},{"name":"Jonathan Huberdeau","teams":["CGY"],"nat":"CAN","playerId":8476456},{"name":"Jonathan Marchessault","teams":["NSH"],"nat":"CAN","playerId":8476539},{"name":"Dennis Cholowski","teams":["NJD"],"nat":"CAN","playerId":8479395},{"name":"Jack Roslovic","teams":["EDM"],"nat":"USA","playerId":8478458},{"name":"Corey Perry","teams":["TBL"],"nat":"CAN","playerId":8470621},{"name":"Dean Kukan","teams":[],"nat":"SUI","playerId":8478567},{"name":"Filip Hronek","teams":["VAN"],"nat":"CZE","playerId":8479425},{"name":"Dominik Simon","teams":[],"nat":"CZE","playerId":8478866},{"name":"Cory Conacher","teams":[],"nat":"CAN","playerId":8476195},{"name":"Chris Wagner","teams":[],"nat":"USA","playerId":8475780},{"name":"Jeff Carter","teams":[],"nat":"CAN","playerId":8470604},{"name":"Denis Gurianov","teams":[],"nat":"RUS","playerId":8478495},{"name":"Alex Killorn","teams":["ANA"],"nat":"CAN","playerId":8473986},{"name":"Oliver Kylington","teams":[],"nat":"SWE","playerId":8478430},{"name":"Tyler Toffoli","teams":["SJS"],"nat":"CAN","playerId":8475726},{"name":"Tim Heed","teams":[],"nat":"SWE","playerId":8475841},{"name":"Dylan Larkin","teams":["DET"],"nat":"USA","playerId":8477946},{"name":"Nicholas Shore","teams":[],"nat":"USA","playerId":8476406},{"name":"Calvin Thurkauf","teams":[],"nat":"SUI","playerId":8479557},{"name":"Joe Hicketts","teams":["LAK"],"nat":"CAN","playerId":8478176},{"name":"Vladislav Gavrikov","teams":["NYR"],"nat":"RUS","playerId":8478882},{"name":"Adam Boqvist","teams":["NYI"],"nat":"SWE","playerId":8480871},{"name":"Colton Sissons","teams":["VGK"],"nat":"CAN","playerId":8476925},{"name":"Michal Kempny","teams":[],"nat":"CZE","playerId":8479482},{"name":"Sonny Milano","teams":["WSH"],"nat":"USA","playerId":8477947},{"name":"Brendan Gaunce","teams":["CBJ"],"nat":"CAN","playerId":8476867},{"name":"Miro Heiskanen","teams":["DAL"],"nat":"FIN","playerId":8480036},{"name":"Dylan Strome","teams":["WSH"],"nat":"CAN","playerId":8478440},{"name":"Victor Rask","teams":[],"nat":"SWE","playerId":8476437},{"name":"Blake Wheeler","teams":[],"nat":"USA","playerId":8471218},{"name":"Chad Ruhwedel","teams":[],"nat":"USA","playerId":8477244},{"name":"Anthony Duclair","teams":["NYI"],"nat":"CAN","playerId":8477407},{"name":"Oscar Fantenberg","teams":[],"nat":"SWE","playerId":8480147},{"name":"Tyler Bozak","teams":[],"nat":"CAN","playerId":8475098},{"name":"Nick Jensen","teams":["OTT"],"nat":"USA","playerId":8475324},{"name":"William Carrier","teams":["CAR"],"nat":"CAN","playerId":8477478},{"name":"Bryan Little","teams":[],"nat":"CAN","playerId":8473412},{"name":"Kole Sherwood","teams":[],"nat":"USA","playerId":8478949},{"name":"Brayden Schenn","teams":["NYI"],"nat":"CAN","playerId":8475170},{"name":"Mike Matheson","teams":["MTL"],"nat":"CAN","playerId":8476875},{"name":"Joseph Blandisi","teams":[],"nat":"CAN","playerId":8477010},{"name":"Andrej Sekera","teams":[],"nat":"SVK","playerId":8471284},{"name":"David Gustafsson","teams":["WPG"],"nat":"SWE","playerId":8481019},{"name":"Cody Goloubef","teams":[],"nat":"CAN","playerId":8474597},{"name":"Brad Marchand","teams":["FLA"],"nat":"CAN","playerId":8473419},{"name":"Ross Johnston","teams":["ANA"],"nat":"CAN","playerId":8477527},{"name":"J.T. Miller","teams":["NYR"],"nat":"USA","playerId":8476468},{"name":"Miikka Salomaki","teams":[],"nat":"FIN","playerId":8476447},{"name":"Nick Schmaltz","teams":["UTA"],"nat":"USA","playerId":8477951},{"name":"Adam Erne","teams":["DAL"],"nat":"USA","playerId":8477454},{"name":"Austin Czarnik","teams":[],"nat":"USA","playerId":8478512},{"name":"Cale Makar","teams":["COL"],"nat":"CAN","playerId":8480069},{"name":"Tomas Jurco","teams":[],"nat":"SVK","playerId":8476430},{"name":"Jason Demers","teams":[],"nat":"CAN","playerId":8474218},{"name":"Travis Zajac","teams":[],"nat":"CAN","playerId":8471233},{"name":"Kailer Yamamoto","teams":["UTA"],"nat":"USA","playerId":8479977},{"name":"Adam Johnson","teams":[],"nat":"USA","playerId":8480341},{"name":"Erik Haula","teams":["NSH"],"nat":"FIN","playerId":8475287},{"name":"Andreas Johnsson","teams":[],"nat":"SWE","playerId":8477341},{"name":"Phillip Di Giuseppe","teams":["WPG"],"nat":"CAN","playerId":8476858},{"name":"Alex Iafallo","teams":["WPG"],"nat":"USA","playerId":8480113},{"name":"Charlie McAvoy","teams":["BOS"],"nat":"USA","playerId":8479325},{"name":"Jakub Vrana","teams":[],"nat":"CZE","playerId":8477944},{"name":"Dmytro Timashov","teams":[],"nat":"UKR","playerId":8478857},{"name":"Mike Green","teams":[],"nat":"CAN","playerId":8471242,"birthDate":"1985-10-12"},{"name":"Carter Rowney","teams":[],"nat":"CAN","playerId":8477240},{"name":"Zack MacEwen","teams":["NJD"],"nat":"CAN","playerId":8479772},{"name":"Cameron Hughes","teams":["DAL"],"nat":"CAN","playerId":8478888},{"name":"Libor Hajek","teams":[],"nat":"CZE","playerId":8479333},{"name":"Tim Schaller","teams":[],"nat":"USA","playerId":8477213},{"name":"David Kampf","teams":["WSH"],"nat":"CZE","playerId":8480144},{"name":"Leon Draisaitl","teams":["EDM"],"nat":"GER","playerId":8477934},{"name":"Carl Dahlstrom","teams":[],"nat":"SWE","playerId":8477472},{"name":"Niko Mikkola","teams":["FLA"],"nat":"FIN","playerId":8478859},{"name":"Conor Sheary","teams":["NYR"],"nat":"USA","playerId":8477839},{"name":"Steven Stamkos","teams":["NSH"],"nat":"CAN","playerId":8474564},{"name":"Alex Goligoski","teams":[],"nat":"USA","playerId":8471274},{"name":"Shea Weber","teams":["CHI"],"nat":"CAN","playerId":8470642},{"name":"Martin Fehervary","teams":["WSH"],"nat":"SVK","playerId":8480796},{"name":"Steven Santini","teams":["TBL"],"nat":"USA","playerId":8477463},{"name":"Brendan Smith","teams":["CBJ"],"nat":"CAN","playerId":8474090},{"name":"Kyle Clifford","teams":[],"nat":"CAN","playerId":8475160},{"name":"Oskar Lindblom","teams":[],"nat":"SWE","playerId":8478067},{"name":"Nikita Gusev","teams":[],"nat":"RUS","playerId":8477038},{"name":"Juuso Riikola","teams":[],"nat":"FIN","playerId":8480945},{"name":"Ryan Lindgren","teams":["SEA"],"nat":"USA","playerId":8479324},{"name":"Ryan Nugent-Hopkins","teams":["EDM"],"nat":"CAN","playerId":8476454},{"name":"Anthony Richard","teams":["PHI"],"nat":"CAN","playerId":8478409},{"name":"Zach Trotman","teams":[],"nat":"USA","playerId":8475902},{"name":"Oliver Bjorkstrand","teams":["TBL"],"nat":"DNK","playerId":8477416},{"name":"Roman Josi","teams":["NSH"],"nat":"SUI","playerId":8474600},{"name":"Reilly Smith","teams":["VGK"],"nat":"CAN","playerId":8475191},{"name":"Sven Baertschi","teams":[],"nat":"SUI","playerId":8476466},{"name":"Nick Bjugstad","teams":["NJD"],"nat":"USA","playerId":8475760},{"name":"Michael Grabner","teams":[],"nat":"AUT","playerId":8473546},{"name":"Anze Kopitar","teams":["LAK"],"nat":"SVN","playerId":8471685},{"name":"Martin Marincin","teams":[],"nat":"SVK","playerId":8475716},{"name":"Marc Staal","teams":[],"nat":"CAN","playerId":8471686},{"name":"Gabriel Vilardi","teams":["WPG"],"nat":"CAN","playerId":8480014},{"name":"Henrik Borgstrom","teams":[],"nat":"FIN","playerId":8479404},{"name":"Alex Biega","teams":[],"nat":"CAN","playerId":8473415},{"name":"Luke Glendening","teams":["PHI"],"nat":"USA","playerId":8476822},{"name":"Brendan Lemieux","teams":[],"nat":"USA","playerId":8477962},{"name":"Daniel Sprong","teams":[],"nat":"CAN","playerId":8478466},{"name":"Tage Thompson","teams":["BUF"],"nat":"USA","playerId":8479420},{"name":"Ron Hainsey","teams":[],"nat":"USA","playerId":8468493},{"name":"Jakob Lilja","teams":[],"nat":"SWE","playerId":8481650},{"name":"Dakota Mermis","teams":["TOR"],"nat":"USA","playerId":8477541},{"name":"Mattias Janmark","teams":["EDM"],"nat":"SWE","playerId":8477406},{"name":"Madison Bowey","teams":[],"nat":"CAN","playerId":8477474},{"name":"Alexandre Carrier","teams":["MTL"],"nat":"CAN","playerId":8478851},{"name":"Adam Larsson","teams":["SEA"],"nat":"SWE","playerId":8476457},{"name":"Devin Shore","teams":[],"nat":"CAN","playerId":8476913},{"name":"Curtis Lazar","teams":["EDM"],"nat":"CAN","playerId":8477508},{"name":"Seth Jones","teams":["FLA"],"nat":"USA","playerId":8477495},{"name":"Mark Stone","teams":["VGK"],"nat":"CAN","playerId":8475913},{"name":"Mikko Koivu","teams":[],"nat":"FIN","playerId":8469459},{"name":"Ian Cole","teams":["UTA"],"nat":"USA","playerId":8474013},{"name":"Jonas Siegenthaler","teams":["NJD"],"nat":"SUI","playerId":8478399},{"name":"Zack Smith","teams":[],"nat":"CAN","playerId":8474250},{"name":"Christian Djoos","teams":[],"nat":"SWE","playerId":8477043},{"name":"Kris Russell","teams":[],"nat":"CAN","playerId":8471729},{"name":"Justin Schultz","teams":[],"nat":"CAN","playerId":8474602},{"name":"Andrew Ladd","teams":[],"nat":"CAN","playerId":8471217},{"name":"Samuel Girard","teams":["PIT"],"nat":"CAN","playerId":8479398},{"name":"Dylan Gambrell","teams":[],"nat":"USA","playerId":8479580},{"name":"Gage Quinney","teams":[],"nat":"USA","playerId":8479748},{"name":"Kale Clague","teams":["WPG"],"nat":"CAN","playerId":8479348},{"name":"Joe Pavelski","teams":[],"nat":"USA","playerId":8470794},{"name":"Andrew Agozzino","teams":["UTA"],"nat":"CAN","playerId":8475461},{"name":"Karson Kuhlman","teams":[],"nat":"USA","playerId":8480901},{"name":"Jack Eichel","teams":["VGK"],"nat":"USA","playerId":8478403},{"name":"Jakob Silfverberg","teams":[],"nat":"SWE","playerId":8475164},{"name":"Christian Jaros","teams":[],"nat":"SVK","playerId":8478868},{"name":"Mason Marchment","teams":["CBJ"],"nat":"CAN","playerId":8478975},{"name":"Brandon Carlo","teams":["TOR"],"nat":"USA","playerId":8478443},{"name":"Alan Quine","teams":[],"nat":"CAN","playerId":8476409},{"name":"Jordan Kyrou","teams":["STL"],"nat":"CAN","playerId":8479385},{"name":"Christian Folin","teams":[],"nat":"SWE","playerId":8477850},{"name":"Tomas Tatar","teams":[],"nat":"SVK","playerId":8475193},{"name":"Max Domi","teams":["TOR"],"nat":"CAN","playerId":8477503},{"name":"Trent Frederic","teams":["EDM"],"nat":"USA","playerId":8479365},{"name":"Gerry Mayhew","teams":[],"nat":"USA","playerId":8479933},{"name":"Brendan Guhle","teams":[],"nat":"CAN","playerId":8478425},{"name":"Brett Kulak","teams":["COL"],"nat":"CAN","playerId":8476967},{"name":"Jay Bouwmeester","teams":[],"nat":"CAN","playerId":8470151},{"name":"Charlie Coyle","teams":["CBJ"],"nat":"USA","playerId":8475745},{"name":"Sidney Crosby","teams":["PIT"],"nat":"CAN","playerId":8471675},{"name":"Michael McLeod","teams":[],"nat":"CAN","playerId":8479415},{"name":"Mitchell Stephens","teams":["SEA"],"nat":"CAN","playerId":8478477},{"name":"Joel Hanley","teams":["CGY"],"nat":"CAN","playerId":8477810},{"name":"Jake Muzzin","teams":[],"nat":"CAN","playerId":8474162},{"name":"Karl Alzner","teams":[],"nat":"CAN","playerId":8473991},{"name":"Zach Werenski","teams":["CBJ"],"nat":"USA","playerId":8478460},{"name":"Calvin de Haan","teams":[],"nat":"CAN","playerId":8475177},{"name":"Trevor Carrick","teams":[],"nat":"CAN","playerId":8476953},{"name":"Joona Luoto","teams":[],"nat":"FIN","playerId":8481649},{"name":"Rickard Rakell","teams":["PIT"],"nat":"SWE","playerId":8476483},{"name":"Claude Giroux","teams":["OTT"],"nat":"CAN","playerId":8473512},{"name":"Nikita Kucherov","teams":["TBL"],"nat":"RUS","playerId":8476453},{"name":"William Nylander","teams":["TOR"],"nat":"SWE","playerId":8477939},{"name":"Travis Dermott","teams":[],"nat":"CAN","playerId":8478408}]